odoo/addons/crm_partner_creator_rest_api/__init__.py
odoo/addons/crm_partner_creator_rest_api/__manifest__.py
odoo/addons/crm_partner_creator_rest_api/services/__init__.py
odoo/addons/crm_partner_creator_rest_api/services/crm_lead_services.py
odoo/addons/crm_partner_creator_rest_api/services/schemas.py
odoo12_addon_crm_partner_creator_rest_api-12.0.0.0.1.dist-info/METADATA
odoo12_addon_crm_partner_creator_rest_api-12.0.0.0.1.dist-info/WHEEL
odoo12_addon_crm_partner_creator_rest_api-12.0.0.0.1.dist-info/top_level.txt
odoo12_addon_crm_partner_creator_rest_api-12.0.0.0.1.dist-info/RECORD
