Metadata-Version: 2.1
Name: odoo12-addon-crm-partner-creator-rest-api
Version: 12.0.0.0.1
Summary: Expose crm partner_creator config on API
Home-page: https://git.coopdevs.org/coopdevs/odoo/odoo-addons/enhancements/enhancements-crm
Author: Coopdevs Treball SCCL
Classifier: Programming Language :: Python
Classifier: Framework :: Odoo
Classifier: Framework :: Odoo :: 12.0
Requires-Python: >=3.5
Requires-Dist: odoo12-addon-crm-partner-creator
Requires-Dist: odoo12-addon-crm-rest-api
Requires-Dist: odoo (<12.1dev,>=12.0a)
